mahkrab/__init__.py
mahkrab/cli.py
mahkrab/constants.py
mahkrab/assets/headerTable.py
mahkrab/assets/terry.txt
mahkrab/func/__init__.py
mahkrab/func/asmexec.py
mahkrab/func/binexec.py
mahkrab/func/cexec.py
mahkrab/func/og.py
mahkrab/func/pyexec.py
mahkrab/func/run.py
mahkrab/func/terry.py
mahkrab/func/tree.py
mahkrab/tools/__init__.py
mahkrab/tools/findDependencies.py
mahkrab/tools/getversion.py
mahkrab/tools/oscheck.py
mahkrab/tools/parser.py
mahkrab/tools/decorators/timers.py
mahkrab-0.0.2.dist-info/licenses/LICENSE
mahkrab-0.0.2.dist-info/METADATA
mahkrab-0.0.2.dist-info/WHEEL
mahkrab-0.0.2.dist-info/entry_points.txt
mahkrab-0.0.2.dist-info/top_level.txt
mahkrab-0.0.2.dist-info/RECORD
