Metadata-Version: 2.4
Name: mahkrab
Version: 0.0.2
Summary: MAHKRAB CLI tool
Author: Oliver Barkham
License-Expression: MIT
Project-URL: Homepage, https://github.com/olibark/MahkrabCLI
Requires-Python: >=3.10
License-File: LICENSE
Dynamic: license-file
